<annotation verified="yes">
  <folder>wet_full</folder>
  <filename>puddle.78</filename>
  <path>/Users/elizabeth/Box Sync/water/wet_full/puddle.78.jpg</path>
  <source>
    <database>Unknown</database>
  </source>
  <size>
    <width>4032</width>
    <height>3024</height>
    <depth>3</depth>
  </size>
  <segmented>0</segmented>
  <object>
    <name>water</name>
    <pose>Unspecified</pose>
    <truncated>0</truncated>
    <difficult>0</difficult>
    <bndbox>
      <xmin>1050</xmin>
      <ymin>1232</ymin>
      <xmax>2022</xmax>
      <ymax>2200</ymax>
    </bndbox>
  </object>
  <object>
    <name>sky</name>
    <pose>Unspecified</pose>
    <truncated>1</truncated>
    <difficult>0</difficult>
    <bndbox>
      <xmin>1</xmin>
      <ymin>763</ymin>
      <xmax>800</xmax>
      <ymax>2549</ymax>
    </bndbox>
  </object>
  <object>
    <name>vegetation</name>
    <pose>Unspecified</pose>
    <truncated>1</truncated>
    <difficult>0</difficult>
    <bndbox>
      <xmin>241</xmin>
      <ymin>1</ymin>
      <xmax>2659</xmax>
      <ymax>773</ymax>
    </bndbox>
  </object>
  <object>
    <name>vegetation</name>
    <pose>Unspecified</pose>
    <truncated>0</truncated>
    <difficult>0</difficult>
    <bndbox>
      <xmin>1186</xmin>
      <ymin>695</ymin>
      <xmax>2673</xmax>
      <ymax>1305</ymax>
    </bndbox>
  </object>
  <object>
    <name>vegetation</name>
    <pose>Unspecified</pose>
    <truncated>0</truncated>
    <difficult>0</difficult>
    <bndbox>
      <xmin>770</xmin>
      <ymin>1718</ymin>
      <xmax>1104</xmax>
      <ymax>2997</ymax>
    </bndbox>
  </object>
  <object>
    <name>vegetation</name>
    <pose>Unspecified</pose>
    <truncated>0</truncated>
    <difficult>0</difficult>
    <bndbox>
      <xmin>1093</xmin>
      <ymin>2282</ymin>
      <xmax>1318</xmax>
      <ymax>3010</ymax>
    </bndbox>
  </object>
</annotation>
