<annotation>
	<folder>smithtown</folder>
	<filename>DJI_0104_5</filename>
	<path>/Volumes/WD Elements Case/smithtown/DJI_0104_5</path>
	<source>
		<database>Unknown</database>
	</source>
	<size>
		<width>500</width>
		<height>500</height>
		<depth>3</depth>
	</size>
	<segmented>0</segmented>
	<object>
		<name>toy</name>
		<pose>Unspecified</pose>
		<truncated>0</truncated>
		<difficult>0</difficult>
		<bndbox>
			<xmin>147</xmin>
			<ymin>204</ymin>
			<xmax>170</xmax>
			<ymax>228</ymax>
		</bndbox>
	</object>
	<object>
		<name>toy</name>
		<pose>Unspecified</pose>
		<truncated>0</truncated>
		<difficult>0</difficult>
		<bndbox>
			<xmin>168</xmin>
			<ymin>193</ymin>
			<xmax>195</xmax>
			<ymax>229</ymax>
		</bndbox>
	</object>
	<object>
		<name>toy</name>
		<pose>Unspecified</pose>
		<truncated>0</truncated>
		<difficult>0</difficult>
		<bndbox>
			<xmin>226</xmin>
			<ymin>265</ymin>
			<xmax>244</xmax>
			<ymax>292</ymax>
		</bndbox>
	</object>
	<object>
		<name>toy</name>
		<pose>Unspecified</pose>
		<truncated>0</truncated>
		<difficult>0</difficult>
		<bndbox>
			<xmin>184</xmin>
			<ymin>263</ymin>
			<xmax>211</xmax>
			<ymax>294</ymax>
		</bndbox>
	</object>
	<object>
		<name>toy</name>
		<pose>Unspecified</pose>
		<truncated>0</truncated>
		<difficult>0</difficult>
		<bndbox>
			<xmin>182</xmin>
			<ymin>222</ymin>
			<xmax>207</xmax>
			<ymax>246</ymax>
		</bndbox>
	</object>
	<object>
		<name>toy</name>
		<pose>Unspecified</pose>
		<truncated>0</truncated>
		<difficult>0</difficult>
		<bndbox>
			<xmin>61</xmin>
			<ymin>356</ymin>
			<xmax>163</xmax>
			<ymax>447</ymax>
		</bndbox>
	</object>
</annotation>
