<annotation>
	<folder>smithtown</folder>
	<filename>DJI_0175_18</filename>
	<path>/Volumes/WD Elements Case/smithtown/DJI_0175_18</path>
	<source>
		<database>Unknown</database>
	</source>
	<size>
		<width>500</width>
		<height>500</height>
		<depth>3</depth>
	</size>
	<segmented>0</segmented>
	<object>
		<name>flower pot</name>
		<pose>Unspecified</pose>
		<truncated>0</truncated>
		<difficult>0</difficult>
		<bndbox>
			<xmin>320</xmin>
			<ymin>408</ymin>
			<xmax>350</xmax>
			<ymax>436</ymax>
		</bndbox>
	</object>
	<object>
		<name>flower pot</name>
		<pose>Unspecified</pose>
		<truncated>0</truncated>
		<difficult>0</difficult>
		<bndbox>
			<xmin>354</xmin>
			<ymin>432</ymin>
			<xmax>375</xmax>
			<ymax>455</ymax>
		</bndbox>
	</object>
</annotation>
