<annotation verified="no">
  <folder>images</folder>
  <filename>IMG_3795</filename>
  <path>/Users/elizabeth/Box Sync/deeplearningcourse/elizabeth/data/other_water/images/IMG_3795.JPG</path>
  <source>
    <database>Unknown</database>
  </source>
  <size>
    <width>4032</width>
    <height>3024</height>
    <depth>3</depth>
  </size>
  <segmented>0</segmented>
  <object>
    <name>container</name>
    <pose>Unspecified</pose>
    <truncated>1</truncated>
    <difficult>0</difficult>
    <bndbox>
      <xmin>1</xmin>
      <ymin>176</ymin>
      <xmax>2288</xmax>
      <ymax>2859</ymax>
    </bndbox>
  </object>
  <object>
    <name>water</name>
    <pose>Unspecified</pose>
    <truncated>0</truncated>
    <difficult>0</difficult>
    <bndbox>
      <xmin>867</xmin>
      <ymin>934</ymin>
      <xmax>2197</xmax>
      <ymax>2297</ymax>
    </bndbox>
  </object>
  <object>
    <name>water</name>
    <pose>Unspecified</pose>
    <truncated>0</truncated>
    <difficult>0</difficult>
    <bndbox>
      <xmin>2834</xmin>
      <ymin>1105</ymin>
      <xmax>3580</xmax>
      <ymax>1751</ymax>
    </bndbox>
  </object>
  <object>
    <name>container</name>
    <pose>Unspecified</pose>
    <truncated>1</truncated>
    <difficult>0</difficult>
    <bndbox>
      <xmin>2747</xmin>
      <ymin>526</ymin>
      <xmax>4032</xmax>
      <ymax>2176</ymax>
    </bndbox>
  </object>
  <object>
    <name>container</name>
    <pose>Unspecified</pose>
    <truncated>1</truncated>
    <difficult>0</difficult>
    <bndbox>
      <xmin>2122</xmin>
      <ymin>1</ymin>
      <xmax>3665</xmax>
      <ymax>867</ymax>
    </bndbox>
  </object>
</annotation>
