<annotation>
	<folder>Mavic Week 2</folder>
	<filename>DJI_0026_20.JPG</filename>
	<path>/Volumes/WD Elements Case/Mavic/Fieldwork pt 2/Harrison/Mavic Week 2/DJI_0026_20.JPG</path>
	<source>
		<database>Unknown</database>
	</source>
	<size>
		<width>512</width>
		<height>512</height>
		<depth>3</depth>
	</size>
	<segmented>0</segmented>
	<object>
		<name>recycling bin</name>
		<pose>Unspecified</pose>
		<truncated>1</truncated>
		<difficult>0</difficult>
		<bndbox>
			<xmin>260</xmin>
			<ymin>456</ymin>
			<xmax>345</xmax>
			<ymax>512</ymax>
		</bndbox>
	</object>
	<object>
		<name>tarp</name>
		<pose>Unspecified</pose>
		<truncated>1</truncated>
		<difficult>0</difficult>
		<bndbox>
			<xmin>185</xmin>
			<ymin>344</ymin>
			<xmax>271</xmax>
			<ymax>512</ymax>
		</bndbox>
	</object>
	<object>
		<name>gutter</name>
		<pose>Unspecified</pose>
		<truncated>0</truncated>
		<difficult>0</difficult>
		<bndbox>
			<xmin>173</xmin>
			<ymin>42</ymin>
			<xmax>267</xmax>
			<ymax>87</ymax>
		</bndbox>
	</object>
</annotation>
